splight_lib/__init__.py
splight_lib/config.py
splight_lib/conftest.py
splight_lib/constants.py
splight_lib/encryption.py
splight_lib/settings.py
splight_lib/version.py
splight_lib/abstract/__init__.py
splight_lib/abstract/client.py
splight_lib/auth/__init__.py
splight_lib/auth/token.py
splight_lib/client/__init__.py
splight_lib/client/exceptions.py
splight_lib/client/database/__init__.py
splight_lib/client/database/abstract.py
splight_lib/client/database/builder.py
splight_lib/client/database/classmap.py
splight_lib/client/database/remote_client.py
splight_lib/client/datalake/__init__.py
splight_lib/client/datalake/builder.py
splight_lib/client/datalake/common/__init__.py
splight_lib/client/datalake/common/abstract.py
splight_lib/client/datalake/common/buffer.py
splight_lib/client/datalake/v3/__init__.py
splight_lib/client/datalake/v3/builder.py
splight_lib/client/datalake/v3/classmap.py
splight_lib/client/datalake/v3/constants.py
splight_lib/client/datalake/v3/exceptions.py
splight_lib/client/datalake/v3/remote_client.py
splight_lib/client/datalake/v4/__init__.py
splight_lib/client/datalake/v4/builder.py
splight_lib/client/datalake/v4/exceptions.py
splight_lib/client/datalake/v4/generic.py
splight_lib/client/datalake/v4/remote_client.py
splight_lib/client/hub/__init__.py
splight_lib/client/hub/abstract.py
splight_lib/client/hub/client.py
splight_lib/client/tests/test_database.py
splight_lib/client/tests/test_datalake.py
splight_lib/component/__init__.py
splight_lib/component/abstract.py
splight_lib/component/exceptions.py
splight_lib/component/spec.py
splight_lib/component/tests/test_spec.py
splight_lib/execution/__init__.py
splight_lib/execution/engine.py
splight_lib/execution/exceptions.py
splight_lib/execution/scheduling.py
splight_lib/execution/task.py
splight_lib/execution/trigger.py
splight_lib/execution/tests/test_execution.py
splight_lib/execution/tests/test_scheduling.py
splight_lib/logging/__init__.py
splight_lib/logging/_internal.py
splight_lib-5.24.1.dist-info/METADATA
splight_lib-5.24.1.dist-info/WHEEL
splight_lib-5.24.1.dist-info/licenses/LICENSE.txt
splight_lib-5.24.1.dist-info/RECORD
