Metadata-Version: 2.4
Name: splight-lib
Version: 5.24.1
Summary: Splight Python Library
Author-email: Splight Dev <dev@splight.com>
License-File: LICENSE.txt
Requires-Python: <3.13,>=3.10
Requires-Dist: apscheduler==3.10.4
Requires-Dist: concurrent-log-handler==0.9.21
Requires-Dist: cryptography==44.0.1
Requires-Dist: email-validator<3.0.0,>=2.1.0.post1
Requires-Dist: furl==2.1.3
Requires-Dist: geojson-pydantic==1.0.1
Requires-Dist: hexbytes==0.2.2
Requires-Dist: httpx==0.28.1
Requires-Dist: jinja2==3.1.4
Requires-Dist: mergedeep==1.3.4
Requires-Dist: numpy==1.26.0
Requires-Dist: pandas==2.2.3
Requires-Dist: parameterized==0.8.1
Requires-Dist: pathspec==0.11.1
Requires-Dist: progressbar2==4.4.1
Requires-Dist: py7zr==0.20.8
Requires-Dist: pydantic-settings==2.0.3
Requires-Dist: pydantic==2.4.2
Requires-Dist: pytz==2025.2
Requires-Dist: pyyaml==6.0.1
Requires-Dist: requests>=2.32.5
Requires-Dist: retry==0.9.2
Requires-Dist: simplejson==3.17.6
Requires-Dist: strenum==0.4.9
Requires-Dist: typer==0.15.1
Requires-Dist: typing-extensions<5.0.0,>=4.6.1
